explicit_sql/__init__.py
explicit_sql/explicit_sql.py
explicit_sql/py.typed
explicit_sql-0.0.5.dist-info/METADATA
explicit_sql-0.0.5.dist-info/WHEEL
explicit_sql-0.0.5.dist-info/licenses/LICENSE
explicit_sql-0.0.5.dist-info/RECORD
