Metadata-Version: 2.4
Name: explicit-sql
Version: 0.0.5
Summary: Human mind friendly SQL generator
Author-email: Ivan Zakutnii <zakutnii.ivan@gmail.com>
License-Expression: MIT
License-File: LICENSE
Keywords: database,duckdb,orm-alternative,python,python310,python311,python312,sql,sql-generator,type-safe,typeddict
Classifier: Development Status :: 3 - Alpha
Classifier: Intended Audience :: Developers
Classifier: License :: OSI Approved :: MIT License
Classifier: Operating System :: OS Independent
Classifier: Programming Language :: Python
Classifier: Programming Language :: Python :: 3
Classifier: Programming Language :: Python :: 3.10
Classifier: Programming Language :: Python :: 3.11
Classifier: Programming Language :: Python :: 3.12
Classifier: Programming Language :: SQL
Classifier: Topic :: Database
Classifier: Topic :: Software Development
Classifier: Topic :: Software Development :: Libraries
Classifier: Topic :: Software Development :: Libraries :: Python Modules
Classifier: Typing :: Typed
Requires-Python: >=3.10
